README.md
setup.cfg
setup.py
davidException.egg-info/PKG-INFO
davidException.egg-info/SOURCES.txt
davidException.egg-info/dependency_links.txt
davidException.egg-info/top_level.txt
package/__init__.py
package/error.py
package/validates.py